CHANGELOG.md
LICENSE.txt
README.md
sanic_synchro_ctx/__init__.py
sanic_synchro_ctx/extension.py
sanic_synchro_ctx/redisns.py
sanic_synchro_ctx/syncns.py
sanic_synchro_ctx-0.1.0.dist-info/LICENSE.txt
sanic_synchro_ctx-0.1.0.dist-info/WHEEL
sanic_synchro_ctx-0.1.0.dist-info/METADATA
sanic_synchro_ctx-0.1.0.dist-info/RECORD
