Metadata-Version: 2.1
Name: sanic-synchro-ctx
Version: 0.1.0
Summary: Synchronize Sanic contects between instances when using multiple workers
Home-page: https://github.com/ashleysommer/sanic-synchro-ctx
License: MIT
Keywords: Linked Data,Semantic Web,RDF,Python,SHACL,Shapes,Schema,Validate
Author: Ashley Sommer
Author-email: ashleysommer@gmail.com
Requires-Python: >=3.8.0,<4.0.0
Classifier: Development Status :: 3 - Alpha
Classifier: Intended Audience :: Developers
Classifier: License :: OSI Approved :: MIT License
Classifier: Natural Language :: English
Classifier: Operating System :: OS Independent
Classifier: Programming Language :: Python :: 3
Classifier: Programming Language :: Python :: 3 :: Only
Classifier: Programming Language :: Python :: 3.10
Classifier: Programming Language :: Python :: 3.8
Classifier: Programming Language :: Python :: 3.9
Classifier: Programming Language :: Python :: Implementation :: CPython
Classifier: Programming Language :: Python :: Implementation :: PyPy
Classifier: Topic :: Software Development :: Libraries :: Python Modules
Classifier: Topic :: Utilities
Provides-Extra: dev-lint
Provides-Extra: dev-type-checking
Provides-Extra: redis
Requires-Dist: aioredis[hiredis] (>=2.0.1); extra == "redis"
Requires-Dist: hiredis (>=1.0.0); extra == "redis"
Requires-Dist: sanic (>=21.9.3)
Project-URL: Repository, https://github.com/ashleysommer/sanic-synchro-ctx
